LICENSE.txt
MANIFEST.in
README.rst
setup.py
django_doorman.egg-info/PKG-INFO
django_doorman.egg-info/SOURCES.txt
django_doorman.egg-info/dependency_links.txt
django_doorman.egg-info/requires.txt
django_doorman.egg-info/top_level.txt
docs/Makefile
docs/conf.py
docs/index.rst
docs/make.bat
doorman/__init__.py
doorman/backends.py
doorman/checkers.py
doorman/decorators.py
doorman/exceptions.py
doorman/loading.py
doorman/models.py