Metadata-Version: 1.0
Name: django-doorman
Version: 0.1.3
Summary: Flexible permission backend
Home-page: https://github.com/seanbrant/django-doorman
Author: Sean Brant
Author-email: brant.sean@gmail.com
License: BSD
Platform: UNKNOWN
Classifier: Development Status :: 3 - Alpha
Classifier: Environment :: Web Environment
Classifier: Intended Audience :: Developers
Classifier: License :: OSI Approved :: BSD License
Classifier: Operating System :: OS Independent
Classifier: Programming Language :: Python
Classifier: Framework :: Django
